tChat/__init__.py
tChat/__main__.py
tChat/command_line_argument_parser.py
tChat/config.py
tChat/customizer.py
tChat/irc_connection.py
tChat/main.py
tChat/twitch_message_parser.py
tChat-1.0.1.dist-info/LICENSE
tChat-1.0.1.dist-info/METADATA
tChat-1.0.1.dist-info/WHEEL
tChat-1.0.1.dist-info/entry_points.txt
tChat-1.0.1.dist-info/top_level.txt
tChat-1.0.1.dist-info/RECORD
