Metadata-Version: 2.1
Name: tChat
Version: 1.0.1
Summary: A Twitch chat UI for your terminal.
Home-page: https://github.com/HicaroD/tChat
Author: Hícaro
Author-email: hdanrlley1@gmail.com
License: MIT License
Platform: UNKNOWN
Classifier: Programming Language :: Python :: 3
Classifier: License :: OSI Approved :: MIT License
Classifier: Operating System :: OS Independent
Requires-Python: >=3.6
License-File: LICENSE
